gdptools/__init__.py
gdptools/__main__.py
gdptools/agg_gen.py
gdptools/depreciation_utils.py
gdptools/helpers.py
gdptools/utils.py
gdptools/utils_optimized.py
gdptools/weight_gen.py
gdptools/weight_gen_p2p.py
gdptools/zonal_gen.py
gdptools/agg/__init__.py
gdptools/agg/agg_data_writers.py
gdptools/agg/agg_engines.py
gdptools/agg/stats_methods.py
gdptools/agg/zonal_engines.py
gdptools/data/__init__.py
gdptools/data/agg_gen_data.py
gdptools/data/odap_cat_data.py
gdptools/data/user_data.py
gdptools/data/weight_gen_data.py
gdptools/weights/__init__.py
gdptools/weights/calc_weight_engines.py
gdptools-0.3.5.dist-info/METADATA
gdptools-0.3.5.dist-info/WHEEL
gdptools-0.3.5.dist-info/entry_points.txt
gdptools-0.3.5.dist-info/licenses/LICENSE.md
gdptools-0.3.5.dist-info/RECORD
