Metadata-Version: 2.4
Name: gdptools
Version: 0.3.5
Summary: Gdptools
Project-URL: Homepage, https://code.usgs.gov/wma/nhgf/toolsteam/gdptools
Project-URL: Repository, https://code.usgs.gov/wma/nhgf/toolsteam/gdptools
Project-URL: Documentation, https://gdptools.readthedocs.io
Project-URL: Changelog, https://code.usgs.gov/wma/nhgf/toolsteam/gdptools/-/blob/develop/HISTORY.md
Author-email: Richard McDonald <rmcd@usgs.gov>, Anders Hopkins <ahopkins@usgs.gov>, August Schultz <arschultz@usgs.gov>
License-Expression: CC0-1.0
License-File: LICENSE.md
Classifier: Development Status :: 5 - Production/Stable
Classifier: Intended Audience :: Developers
Classifier: Intended Audience :: Science/Research
Classifier: License :: OSI Approved
Classifier: Operating System :: OS Independent
Classifier: Programming Language :: Python :: 3.10
Classifier: Programming Language :: Python :: 3.11
Classifier: Programming Language :: Python :: 3.12
Classifier: Programming Language :: Python :: 3.13
Classifier: Topic :: Scientific/Engineering :: GIS
Classifier: Topic :: Scientific/Engineering :: Information Analysis
Classifier: Topic :: Software Development :: Libraries :: Python Modules
Requires-Python: <3.14,>=3.10
Requires-Dist: bottleneck>=1.3.3
Requires-Dist: click<9,>=8.1
Requires-Dist: dask-geopandas>0.4.1
Requires-Dist: dask>2024.8.0
Requires-Dist: exactextract>=0.3.0
Requires-Dist: fastparquet<=2024.5,>=2024.2
Requires-Dist: geopandas>=0.13.0
Requires-Dist: joblib>=1.4.0
Requires-Dist: netcdf4>=1.5.8
Requires-Dist: numpy>2.0
Requires-Dist: pandas>=2.0.0
Requires-Dist: pyarrow<18.0.0,>=10.0.0
Requires-Dist: pydantic>=2
Requires-Dist: pyproj>=3.3.0
Requires-Dist: pystac<2.0,>=1.10
Requires-Dist: rasterio<1.5.0,>=1.2.9
Requires-Dist: rioxarray<0.21,>=0.15
Requires-Dist: s3fs>=2025.2.0
Requires-Dist: shapely>=2.0
Requires-Dist: statsmodels<1.0,>=0.14
Requires-Dist: tqdm>=4.66.2
Requires-Dist: urllib3>=2.6.0
Requires-Dist: xarray<2025.0.0,>=2024.7.0
Requires-Dist: zarr>=2.12.0
